salt_os10/__init__.py
salt_os10/loader.py
salt_os10/states/__init__.py
salt_os10/states/os10.py
salt_os10-0.0.2.dist-info/LICENSE
salt_os10-0.0.2.dist-info/METADATA
salt_os10-0.0.2.dist-info/WHEEL
salt_os10-0.0.2.dist-info/entry_points.txt
salt_os10-0.0.2.dist-info/top_level.txt
salt_os10-0.0.2.dist-info/RECORD
