Metadata-Version: 2.1
Name: salt-os10
Version: 0.0.2
Summary: Small salt module providing os10.managed, to apply basic config on dell OS10 switches
Home-page: https://github.com/ArcaniteSolutions/salt-os10
Author: Maximilien Cuony
Author-email: maximilien.cuony@arcanite.ch
License: MPL
Platform: UNKNOWN
Classifier: Development Status :: 4 - Beta
Classifier: Intended Audience :: System Administrators
Classifier: License :: OSI Approved :: Mozilla Public License 2.0 (MPL 2.0)
Classifier: Operating System :: Other OS
Classifier: Programming Language :: Python
Classifier: Topic :: System :: Networking
Requires-Dist: sh
